lodestonegpt/__init__.py
lodestonegpt/agent.py
lodestonegpt/aifunc.py
lodestonegpt/constants.py
lodestonegpt/logger.py
lodestonegpt/summarizer.py
lodestonegpt/embeddings/__init__.py
lodestonegpt/embeddings/azure_openai.py
lodestonegpt/embeddings/base.py
lodestonegpt/embeddings/hf.py
lodestonegpt/embeddings/openai_.py
lodestonegpt/loops/__init__.py
lodestonegpt/loops/cli.py
lodestonegpt/loops/repl.py
lodestonegpt/loops/ui.py
lodestonegpt/memory/__init__.py
lodestonegpt/memory/base_memory.py
lodestonegpt/memory/local_memory.py
lodestonegpt/models/__init__.py
lodestonegpt/models/azure_openai.py
lodestonegpt/models/base.py
lodestonegpt/models/hf.py
lodestonegpt/models/llama_cpp.py
lodestonegpt/models/openai_.py
lodestonegpt/models/stable_lm.py
lodestonegpt/tools/__init__.py
lodestonegpt/tools/agent_manager.py
lodestonegpt/tools/base_tool.py
lodestonegpt/tools/browser.py
lodestonegpt/tools/code.py
lodestonegpt/tools/filesystem.py
lodestonegpt/tools/google_search.py
lodestonegpt/tools/math.py
lodestonegpt/tools/memory_manager.py
lodestonegpt/tools/shell.py
lodestonegpt/tools/simple_browser.py
lodestonegpt/tools/user_manager.py
lodestonegpt/utils/__init__.py
lodestonegpt/utils/openai_key.py
lodestonegpt/utils/spinner.py
lodestonegpt/utils/text.py
lodestonegpt-0.0.4.dist-info/LICENSE
lodestonegpt-0.0.4.dist-info/WHEEL
lodestonegpt-0.0.4.dist-info/METADATA
lodestonegpt-0.0.4.dist-info/RECORD
