Metadata-Version: 2.1
Name: lodestonegpt
Version: 0.0.4
Summary: 🤖 Modular Auto-GPT Framework Build For Project Lodestone
Author-email: Silke Pilon <silkepilon2009@gmail.com>, HellishBro <hellishbro@outlook.com>, Levy <Levy@example.com>
Requires-Python: >=3.10
Requires-Dist: openai
Requires-Dist: bs4
Requires-Dist: selenium
Requires-Dist: numpy
Requires-Dist: tiktoken>=0.3.3
Requires-Dist: requests
Requires-Dist: colorama
Requires-Dist: duckduckgo_search>=2.9.4
Requires-Dist: google-api-python-client
Requires-Dist: webdriver_manager
Requires-Dist: simpleeval
Requires-Dist: transformers[hf]
Requires-Dist: sentence_transformers[hf]
Requires-Dist: accelerate[hf]
Requires-Dist: bitsandbytes[hf]
Requires-Dist: torch[hf]
Requires-Dist: python-dotenv
Project-URL: Documentation, https://github.com/SilkePilon/Lodestone/blob/main/README.md
Project-URL: Homepage, https://github.com/SilkePilon/Lodestone
Project-URL: Repository, https://github.com/SilkePilon/Lodestone
